guaijiao/__init__.py
guaijiao/getProxies.py
guaijiao/run.py
guaijiao-1.2.0.data/data/my_data/data_file
guaijiao-1.2.0.dist-info/DESCRIPTION.rst
guaijiao-1.2.0.dist-info/METADATA
guaijiao-1.2.0.dist-info/RECORD
guaijiao-1.2.0.dist-info/WHEEL
guaijiao-1.2.0.dist-info/entry_points.txt
guaijiao-1.2.0.dist-info/metadata.json
guaijiao-1.2.0.dist-info/top_level.txt
